django_ghostdown-0.5.dist-info/DESCRIPTION.rst
django_ghostdown-0.5.dist-info/METADATA
django_ghostdown-0.5.dist-info/RECORD
django_ghostdown-0.5.dist-info/WHEEL
django_ghostdown-0.5.dist-info/pydist.json
django_ghostdown-0.5.dist-info/top_level.txt
ghostdown/__init__.py
ghostdown/compat.py
ghostdown/conf.py
ghostdown/models.py
ghostdown/utils.py
ghostdown/forms/__init__.py
ghostdown/forms/templates.py
ghostdown/forms/widgets.py
ghostdown/models/__init__.py
ghostdown/models/fields.py
ghostdown/static/ghostdown/.DS_Store
ghostdown/static/ghostdown/css/ghostdown.css
ghostdown/static/ghostdown/css/preview.css
ghostdown/static/ghostdown/js/ghostdown.js
ghostdown/static/ghostdown/js/preview.js
